{
  "4theory": {
    "result": "Sie sind Anhänger*in der Vierten Theorie",
    "desc": "Die vierte Theorie ist eine von dem russischen Politologen Aleksandr Dugin entwickelte Ideologie, die nach Liberalismus, Marxismus und Faschismus eine neue politische Theorie finden will."
  },
  "agorism": {
    "result": "Sie sind Agorist*in",
    "desc": "Der Agorismus ist eine von Samuel Edward Konkin III entwickelte Ideologie, die darauf abzielt, eine Gesellschaft zu errichten, in der alle Tauschvorgänge freiwillig sind, und zwar mit Hilfe von gegenwirtschaftlichen Aktivitäten."
  },
  "agsoc": {
    "result": "Sie sind Agrarsozialist*in",
    "desc": "Der Agrarsozialismus ist eine Ideologie, die eine agrarische Lebensweise und ein sozialistisches Wirtschaftssystem miteinander verbinden will, wobei der Schwerpunkt auf der Umverteilung von Land und dem gesellschaftlichen Eigentum an Land liegt."
  },
  "ancap": {
    "result": "Sie sind Anarchokapitalist*in",
    "desc": "Der Anarchokapitalismus, auch Voluntarismus genannt, ist eine Ideologie, die sich für die Schaffung einer staatenlosen Gesellschaft einsetzt, die auf Eigentumsrechten und dem Prinzip der Nicht-Aggression beruht."
  },
  "ancol": {
    "result": "Sie sind Anarchokollektivist*in",
    "desc": ""
  },
  "ancom": {
    "result": "Sie sind Anarchokommunist*in",
    "desc": ""
  },
  "angeo": {
    "result": "Sie sind Geoanarchist*in",
    "desc": ""
  },
  "anprim": {
    "result": "Sie sind Anarcho-Primitivist*in",
    "desc": ""
  },
  "ansynd": {
    "result": "Sie sind Anarchosyndikalist*in",
    "desc": ""
  },
  "bhl": {
    "result": "Sie sind ein*e Mitfühlende*r Liberale*r",
    "desc": ""
  },
  "bordiga": {
    "result": "Sie sind Bordigist*in/Italienische*r Kommunist*in",
    "desc": ""
  },
  "castro": {
    "result": "Sie sind Castroist*in",
    "desc": ""
  },
  "fascism": {
    "result": "Sie sind klassische*r Faschist*in",
    "desc": ""
  },
  "clerfash": {
    "result": "Sie sind Klerikalfaschist*in",
    "desc": ""
  },
  "councom": {
    "result": "Sie sind Rätekommunist*in",
    "desc": ""
  },
  "deleon": {
    "result": "Sie sind De Leonist*in",
    "desc": ""
  },
  "demsoc": {
    "result": "Sie sind demokratische*r Sozialist*in",
    "desc": ""
  },
  "deng": {
    "result": "Sie sind Dengist*in",
    "desc": ""
  },
  "distributism": {
    "result": "Sie sind Distributist*in",
    "desc": "Der Distributivismus ist eine mitte-rechte Ideologie des dritten Weges und der freien Marktwirtschaft."
  },
  "geolib": {
    "result": "Sie sind Geo-Libertarist*in",
    "desc": ""
  },
  "georgism": {
    "result": "Sie sind Georgist*in",
    "desc": ""
  },
  "leftroth": {
    "result": "Sie sind Links-Rothbardianist*in",
    "desc": ""
  },
  "libert": {
    "result": "Sie sind Recht-Libertär",
    "desc": ""
  },
  "libsoc": {
    "result": "Sie sind libertäre*r Sozialist*in",
    "desc": ""
  },
  "lib": {
    "result": "Sie sind Keynesianer*in",
    "desc": ""
  },
  "luxem": {
    "result": "Sie sind Luxemburgist*in",
    "desc": ""
  },
  "lwma": {
    "result": "Sie sind Markt-Anarchist*in des linken Flügels",
    "desc": ""
  },
  "mao": {
    "result": "Sie sind Maoist*in",
    "desc": ""
  },
  "marksoc": {
    "result": "Sie sind Marktsozialist*in",
    "desc": ""
  },
  "minarch": {
    "result": "Sie sind Minarchist*in",
    "desc": ""
  },
  "mlm": {
    "result": "Sie sind Anhänger*in des Marxismus-Leninismus-Maoismus",
    "desc": ""
  },
  "ml": {
    "result": "Sie sind Marxist*in-Leninist*in",
    "desc": ""
  },
  "mutualism": {
    "result": "",
    "desc": ""
  },
  "natan": {
    "result": "Sie sind Mutualist*in",
    "desc": ""
  },
  "natsynd": {
    "result": "Sie sind National-Syndikalist*in",
    "desc": ""
  },
  "nazbol": {
    "result": "Sie sind Nationalbolschewist*in",
    "desc": ""
  },
  "nazcap": {
    "result": "Sie sind Nationalkapitalist*in",
    "desc": ""
  },
  "nazi": {
    "result": "Sie sind Nationalsozialist*in",
    "desc": ""
  },
  "neocon": {
    "result": "",
    "desc": ""
  },
  "neolib": {
    "result": "Sie sind neoliberal",
    "desc": ""
  },
  "orthmarx": {
    "result": "Sie sind Orthodox-Marxistisch",
    "desc": ""
  },
  "paleobert": {
    "result": "Sie sind paleoliberal",
    "desc": ""
  },
  "paleocon": {
    "result": "Sie sind paleokonservativ",
    "desc": ""
  },
  "patcon": {
    "result": "Sie sind paternalistisch konservativ.",
    "desc": ""
  },
  "posadism": {
    "result": "Sie sind Posadismus",
    "desc": ""
  },
  "situationist": {
    "result": "Sie sind Situationist*in",
    "desc": ""
  },
  "socbert": {
    "result": "Sie sind Sozialliberalist*in",
    "desc": ""
  },
  "socdem": {
    "result": "Sie sind Sozialdemokrat*in",
    "desc": ""
  },
  "socgeo": {
    "result": "Sie sind Sozialgeorgist*in",
    "desc": ""
  },
  "socnat": {
    "result": "Sie sind Linksnationalist*in",
    "desc": ""
  },
  "statesoc": {
    "result": "Sie sind Staatssozialist*in",
    "desc": ""
  },
  "strasser": {
    "result": "Sie sind Strasserist*in",
    "desc": ""
  },
  "synd": {
    "result": "Sie sind Syndikalist*in",
    "desc": ""
  },
  "technocracy": {
    "result": "Sie sind Technokrat*in",
    "desc": ""
  },
  "theocracy": {
    "result": "Sie sind Theokrat*in",
    "desc": ""
  },
  "tito": {
    "result": "Sie sind Titoist*in",
    "desc": ""
  },
  "trot": {
    "result": "Sie sind Trotzkist*in",
    "desc": ""
  }
}